setup.py
SCMAccessPlugin.egg-info/PKG-INFO
SCMAccessPlugin.egg-info/SOURCES.txt
SCMAccessPlugin.egg-info/dependency_links.txt
SCMAccessPlugin.egg-info/entry_points.txt
SCMAccessPlugin.egg-info/top_level.txt
scm_access/__init__.py
scm_access/scm_access.py