Metadata-Version: 1.0
Name: SCMAccessPlugin
Version: 2.0
Summary: Trac plugin for SCM access control
Home-page: http://www.02strich.de
Author: Stefan Richter
Author-email: stefan@02strich.de
License: UNKNOWN
Platform: UNKNOWN
Classifier: Development Status :: 5 - Production/Stable
Classifier: Framework :: Trac
Classifier: Intended Audience :: System Administrators
Classifier: License :: OSI Approved :: Python Software Foundation License
Classifier: Programming Language :: Python :: 2
